geode_simplexgeosciences/__init__.py
geode_simplexgeosciences/__init__.pyi
geode_simplexgeosciences/model.py
geode_simplexgeosciences/model.pyi
geode_simplexgeosciences/py.typed
geode_simplexgeosciences/lib64/__init__.pyi
geode_simplexgeosciences/lib64/geode_simplexgeosciences_py_model.cpython-39-x86_64-linux-gnu.so
geode_simplexgeosciences/lib64/geode_simplexgeosciences_py_model.pyi
geode_simplexgeosciences/lib64/libGeode-SimplexGeosciences_model.so
geode_simplexgeosciences-3.2.1.dist-info/METADATA
geode_simplexgeosciences-3.2.1.dist-info/WHEEL
geode_simplexgeosciences-3.2.1.dist-info/top_level.txt
geode_simplexgeosciences-3.2.1.dist-info/RECORD
