Metadata-Version: 2.4
Name: Geode-SimplexGeosciences
Version: 3.2.1
Summary: Geosciences simplex remeshing Geode-solutions OpenGeode module
Author-email: Geode-solutions <contact@geode-solutions.com>
License: Proprietary
Requires-Python: <3.13,>=3.9
Requires-Dist: geode-background==9.*,>=9.6.8
Requires-Dist: geode-common==33.*,>=33.11.2
Requires-Dist: geode-numerics==6.*,>=6.4.3
Requires-Dist: geode-simplex==9.*,>=9.8.4
Requires-Dist: opengeode-core==15.*,>=15.29.0
Requires-Dist: opengeode-geosciences==9.*,>=9.5.0
Requires-Dist: opengeode-inspector==6.*,>=6.8.2
